jupyterlab_in_platform_support/__init__.py
jupyterlab_in_platform_support/_version.py
jupyterlab_in_platform_support/handlers.py
jupyterlab_in_platform_support/labextension/build_log.json
jupyterlab_in_platform_support/labextension/package.json
jupyterlab_in_platform_support/labextension/schemas/jupyterlab-in-platform-support/package.json.orig
jupyterlab_in_platform_support/labextension/schemas/jupyterlab-in-platform-support/plugin.json
jupyterlab_in_platform_support/labextension/static/fb29b6ad8cd60b9112b8.png
jupyterlab_in_platform_support/labextension/static/lib_index_js.08d931de214ec0846e0f.js
jupyterlab_in_platform_support/labextension/static/lib_index_js.08d931de214ec0846e0f.js.map
jupyterlab_in_platform_support/labextension/static/lib_index_js.1f40b2d1c24ecef5a885.js
jupyterlab_in_platform_support/labextension/static/lib_index_js.1f40b2d1c24ecef5a885.js.map
jupyterlab_in_platform_support/labextension/static/lib_index_js.2427eb859422957ebbd8.js
jupyterlab_in_platform_support/labextension/static/lib_index_js.2427eb859422957ebbd8.js.map
jupyterlab_in_platform_support/labextension/static/lib_index_js.27bdc4749b2b20bf4da9.js
jupyterlab_in_platform_support/labextension/static/lib_index_js.27bdc4749b2b20bf4da9.js.map
jupyterlab_in_platform_support/labextension/static/lib_index_js.bd5f20f74c02ec40bc22.js
jupyterlab_in_platform_support/labextension/static/lib_index_js.bd5f20f74c02ec40bc22.js.map
jupyterlab_in_platform_support/labextension/static/lib_index_js.d419bce46b245e9d1306.js
jupyterlab_in_platform_support/labextension/static/lib_index_js.d419bce46b245e9d1306.js.map
jupyterlab_in_platform_support/labextension/static/lib_index_js.e73fd542e8aa2cbb24af.js
jupyterlab_in_platform_support/labextension/static/lib_index_js.e73fd542e8aa2cbb24af.js.map
jupyterlab_in_platform_support/labextension/static/node_modules_emotion_use-insertion-effect-with-fallbacks_dist_emotion-use-insertion-effect-wi-3c9bb40.05b7ce58e9519e3e911b.js
jupyterlab_in_platform_support-0.2.0.dist-info/METADATA
jupyterlab_in_platform_support-0.2.0.dist-info/WHEEL
jupyterlab_in_platform_support-0.2.0.dist-info/licenses/LICENSE
jupyterlab_in_platform_support-0.2.0.dist-info/RECORD
